ublib21/__init__.py
ublib21/base.py
ublib21/exceptions.py
ublib21/common/__init__.py
ublib21/common/cac.py
ublib21/common/cac_types.py
ublib21/common/cbc.py
ublib21/common/ccts_cct.py
ublib21/common/ext.py
ublib21/common/udt.py
ublib21/documents/__init__.py
ublib21/documents/base.py
ublib21/documents/credit_note.py
ublib21/documents/debit_note.py
ublib21/documents/invoice.py
ublib21/validation/validation.py
ublib21/validation/schemes/common/CCTS_CCT_SchemaModule-2.1.xsd
ublib21/validation/schemes/common/UBL-CommonAggregateComponents-2.1.xsd
ublib21/validation/schemes/common/UBL-CommonBasicComponents-2.1.xsd
ublib21/validation/schemes/common/UBL-CommonExtensionComponents-2.1.xsd
ublib21/validation/schemes/common/UBL-CommonSignatureComponents-2.1.xsd
ublib21/validation/schemes/common/UBL-CoreComponentParameters-2.1.xsd
ublib21/validation/schemes/common/UBL-ExtensionContentDataType-2.1.xsd
ublib21/validation/schemes/common/UBL-QualifiedDataTypes-2.1.xsd
ublib21/validation/schemes/common/UBL-SignatureAggregateComponents-2.1.xsd
ublib21/validation/schemes/common/UBL-SignatureBasicComponents-2.1.xsd
ublib21/validation/schemes/common/UBL-UnqualifiedDataTypes-2.1.xsd
ublib21/validation/schemes/common/UBL-XAdESv132-2.1.xsd
ublib21/validation/schemes/common/UBL-XAdESv141-2.1.xsd
ublib21/validation/schemes/common/UBL-xmldsig-core-schema-2.1.xsd
ublib21/validation/schemes/maindoc/UBL-ApplicationResponse-2.1.xsd
ublib21/validation/schemes/maindoc/UBL-AttachedDocument-2.1.xsd
ublib21/validation/schemes/maindoc/UBL-AwardedNotification-2.1.xsd
ublib21/validation/schemes/maindoc/UBL-BillOfLading-2.1.xsd
ublib21/validation/schemes/maindoc/UBL-CallForTenders-2.1.xsd
ublib21/validation/schemes/maindoc/UBL-Catalogue-2.1.xsd
ublib21/validation/schemes/maindoc/UBL-CatalogueDeletion-2.1.xsd
ublib21/validation/schemes/maindoc/UBL-CatalogueItemSpecificationUpdate-2.1.xsd
ublib21/validation/schemes/maindoc/UBL-CataloguePricingUpdate-2.1.xsd
ublib21-0.0.1.dist-info/METADATA
ublib21-0.0.1.dist-info/WHEEL
ublib21-0.0.1.dist-info/top_level.txt
ublib21-0.0.1.dist-info/RECORD
