Metadata-Version: 2.1
Name: ublib21
Version: 0.0.1
Summary: UBL 2.1 python object parsing
Author-email: Ramiro Detke <ramiro.fer.det@gmail.com>, Jessica Natalia Pulido Leon <jenapule@gmail.com>
Classifier: Programming Language :: Python :: 3
Requires-Python: >=3.10
